mip_cvxpy/__init__.py
mip_cvxpy-0.0.2.dist-info/LICENSE
mip_cvxpy-0.0.2.dist-info/METADATA
mip_cvxpy-0.0.2.dist-info/WHEEL
mip_cvxpy-0.0.2.dist-info/top_level.txt
mip_cvxpy-0.0.2.dist-info/RECORD
